<?xml version="1.0" encoding="utf-8"?>
<annotation>
 <filename>
  0225_0742039603_05_WRI-L1_M012.png
 </filename>
 <folder/>
 <path>
  0225_0742039603_05_WRI-L1_M012.png
 </path>
 <segmented>
  0
 </segmented>
 <size/>
 <source>
  <database>
   GRAZPEDWRI-DX
  </database>
 </source>
 <object>
  <bndbox>
   <xmax>
    58
   </xmax>
   <xmin>
    0
   </xmin>
   <ymax>
    1163
   </ymax>
   <ymin>
    1051
   </ymin>
  </bndbox>
  <difficult>
   0
  </difficult>
  <name>
   text
  </name>
  <pose>
   Unspecified
  </pose>
  <truncated>
   0
  </truncated>
 </object>
 <object>
  <bndbox>
   <xmax>
    507
   </xmax>
   <xmin>
    304
   </xmin>
   <ymax>
    508
   </ymax>
   <ymin>
    440
   </ymin>
  </bndbox>
  <difficult>
   0
  </difficult>
  <name>
   fracture
  </name>
  <pose>
   Unspecified
  </pose>
  <truncated>
   0
  </truncated>
 </object>
</annotation>