<?xml version="1.0" encoding="utf-8"?>
<annotation>
 <filename>
  0640_0260971841_05_WRI-L1_F005.png
 </filename>
 <folder/>
 <path>
  0640_0260971841_05_WRI-L1_F005.png
 </path>
 <segmented>
  0
 </segmented>
 <size/>
 <source>
  <database>
   GRAZPEDWRI-DX
  </database>
 </source>
 <object>
  <bndbox>
   <xmax>
    58
   </xmax>
   <xmin>
    40
   </xmin>
   <ymax>
    57
   </ymax>
   <ymin>
    33
   </ymin>
  </bndbox>
  <difficult>
   0
  </difficult>
  <name>
   text
  </name>
  <pose>
   Unspecified
  </pose>
  <truncated>
   0
  </truncated>
 </object>
 <object>
  <bndbox>
   <xmax>
    307
   </xmax>
   <xmin>
    211
   </xmin>
   <ymax>
    506
   </ymax>
   <ymin>
    402
   </ymin>
  </bndbox>
  <difficult>
   0
  </difficult>
  <name>
   fracture
  </name>
  <pose>
   Unspecified
  </pose>
  <truncated>
   0
  </truncated>
 </object>
 <object>
  <bndbox>
   <xmax>
    404
   </xmax>
   <xmin>
    383
   </xmin>
   <ymax>
    572
   </ymax>
   <ymin>
    523
   </ymin>
  </bndbox>
  <difficult>
   0
  </difficult>
  <name>
   text
  </name>
  <pose>
   Unspecified
  </pose>
  <truncated>
   0
  </truncated>
 </object>
 <object>
  <bndbox>
   <xmax>
    144
   </xmax>
   <xmin>
    98
   </xmin>
   <ymax>
    282
   </ymax>
   <ymin>
    244
   </ymin>
  </bndbox>
  <difficult>
   0
  </difficult>
  <name>
   fracture
  </name>
  <pose>
   Unspecified
  </pose>
  <truncated>
   0
  </truncated>
 </object>
</annotation>