<?xml version="1.0" encoding="utf-8"?>
<annotation>
 <filename>
  0691_0530232674_01_WRI-L1_M011.png
 </filename>
 <folder/>
 <path>
  0691_0530232674_01_WRI-L1_M011.png
 </path>
 <segmented>
  0
 </segmented>
 <size/>
 <source>
  <database>
   GRAZPEDWRI-DX
  </database>
 </source>
 <object>
  <bndbox>
   <xmax>
    20
   </xmax>
   <xmin>
    1
   </xmin>
   <ymax>
    409
   </ymax>
   <ymin>
    383
   </ymin>
  </bndbox>
  <difficult>
   0
  </difficult>
  <name>
   text
  </name>
  <pose>
   Unspecified
  </pose>
  <truncated>
   0
  </truncated>
 </object>
 <object>
  <bndbox>
   <xmax>
    46
   </xmax>
   <xmin>
    30
   </xmin>
   <ymax>
    113
   </ymax>
   <ymin>
    87
   </ymin>
  </bndbox>
  <difficult>
   0
  </difficult>
  <name>
   text
  </name>
  <pose>
   Unspecified
  </pose>
  <truncated>
   0
  </truncated>
 </object>
 <object>
  <bndbox>
   <xmax>
    331
   </xmax>
   <xmin>
    195
   </xmin>
   <ymax>
    487
   </ymax>
   <ymin>
    445
   </ymin>
  </bndbox>
  <difficult>
   0
  </difficult>
  <name>
   fracture
  </name>
  <pose>
   Unspecified
  </pose>
  <truncated>
   0
  </truncated>
 </object>
</annotation>