<?xml version="1.0" encoding="utf-8"?>
<annotation>
 <filename>
  0736_0854943912_01_WRI-L2_M012.png
 </filename>
 <folder/>
 <path>
  0736_0854943912_01_WRI-L2_M012.png
 </path>
 <segmented>
  0
 </segmented>
 <size/>
 <source>
  <database>
   GRAZPEDWRI-DX
  </database>
 </source>
 <object>
  <bndbox>
   <xmax>
    108
   </xmax>
   <xmin>
    89
   </xmin>
   <ymax>
    197
   </ymax>
   <ymin>
    157
   </ymin>
  </bndbox>
  <difficult>
   0
  </difficult>
  <name>
   text
  </name>
  <pose>
   Unspecified
  </pose>
  <truncated>
   0
  </truncated>
 </object>
 <object>
  <bndbox>
   <xmax>
    41
   </xmax>
   <xmin>
    5
   </xmin>
   <ymax>
    292
   </ymax>
   <ymin>
    246
   </ymin>
  </bndbox>
  <difficult>
   0
  </difficult>
  <name>
   text
  </name>
  <pose>
   Unspecified
  </pose>
  <truncated>
   0
  </truncated>
 </object>
</annotation>