<?xml version="1.0" encoding="utf-8"?>
<annotation>
 <filename>
  0872_0670339301_01_WRI-R2_M004.png
 </filename>
 <folder/>
 <path>
  0872_0670339301_01_WRI-R2_M004.png
 </path>
 <segmented>
  0
 </segmented>
 <size/>
 <source>
  <database>
   GRAZPEDWRI-DX
  </database>
 </source>
 <object>
  <bndbox>
   <xmax>
    293
   </xmax>
   <xmin>
    207
   </xmin>
   <ymax>
    475
   </ymax>
   <ymin>
    415
   </ymin>
  </bndbox>
  <difficult>
   0
  </difficult>
  <name>
   fracture
  </name>
  <pose>
   Unspecified
  </pose>
  <truncated>
   0
  </truncated>
 </object>
 <object>
  <bndbox>
   <xmax>
    401
   </xmax>
   <xmin>
    381
   </xmin>
   <ymax>
    184
   </ymax>
   <ymin>
    111
   </ymin>
  </bndbox>
  <difficult>
   0
  </difficult>
  <name>
   text
  </name>
  <pose>
   Unspecified
  </pose>
  <truncated>
   0
  </truncated>
 </object>
</annotation>