<?xml version="1.0" encoding="utf-8"?>
<annotation>
 <filename>
  0929_0778433056_01_WRI-R1_M002.png
 </filename>
 <folder/>
 <path>
  0929_0778433056_01_WRI-R1_M002.png
 </path>
 <segmented>
  0
 </segmented>
 <size/>
 <source>
  <database>
   GRAZPEDWRI-DX
  </database>
 </source>
 <object>
  <bndbox>
   <xmax>
    468
   </xmax>
   <xmin>
    441
   </xmin>
   <ymax>
    474
   </ymax>
   <ymin>
    406
   </ymin>
  </bndbox>
  <difficult>
   0
  </difficult>
  <name>
   text
  </name>
  <pose>
   Unspecified
  </pose>
  <truncated>
   0
  </truncated>
 </object>
 <object>
  <bndbox>
   <xmax>
    427
   </xmax>
   <xmin>
    412
   </xmin>
   <ymax>
    653
   </ymax>
   <ymin>
    630
   </ymin>
  </bndbox>
  <difficult>
   0
  </difficult>
  <name>
   text
  </name>
  <pose>
   Unspecified
  </pose>
  <truncated>
   0
  </truncated>
 </object>
 <object>
  <bndbox>
   <xmax>
    200
   </xmax>
   <xmin>
    131
   </xmin>
   <ymax>
    670
   </ymax>
   <ymin>
    638
   </ymin>
  </bndbox>
  <difficult>
   0
  </difficult>
  <name>
   fracture
  </name>
  <pose>
   Unspecified
  </pose>
  <truncated>
   0
  </truncated>
 </object>
</annotation>