<?xml version="1.0" encoding="utf-8"?>
<annotation>
 <filename>
  1049_1227500516_04_WRI-L2_M018.png
 </filename>
 <folder/>
 <path>
  1049_1227500516_04_WRI-L2_M018.png
 </path>
 <segmented>
  0
 </segmented>
 <size/>
 <source>
  <database>
   GRAZPEDWRI-DX
  </database>
 </source>
 <object>
  <bndbox>
   <xmax>
    376
   </xmax>
   <xmin>
    219
   </xmin>
   <ymax>
    533
   </ymax>
   <ymin>
    469
   </ymin>
  </bndbox>
  <difficult>
   0
  </difficult>
  <name>
   fracture
  </name>
  <pose>
   Unspecified
  </pose>
  <truncated>
   0
  </truncated>
 </object>
 <object>
  <bndbox>
   <xmax>
    23
   </xmax>
   <xmin>
    0
   </xmin>
   <ymax>
    84
   </ymax>
   <ymin>
    53
   </ymin>
  </bndbox>
  <difficult>
   0
  </difficult>
  <name>
   text
  </name>
  <pose>
   Unspecified
  </pose>
  <truncated>
   0
  </truncated>
 </object>
 <object>
  <bndbox>
   <xmax>
    380
   </xmax>
   <xmin>
    345
   </xmin>
   <ymax>
    619
   </ymax>
   <ymin>
    447
   </ymin>
  </bndbox>
  <difficult>
   0
  </difficult>
  <name>
   periostealreaction
  </name>
  <pose>
   Unspecified
  </pose>
  <truncated>
   0
  </truncated>
 </object>
</annotation>