<?xml version="1.0" encoding="utf-8"?>
<annotation>
 <filename>
  1136_0745379955_01_WRI-R1_F013.png
 </filename>
 <folder/>
 <path>
  1136_0745379955_01_WRI-R1_F013.png
 </path>
 <segmented>
  0
 </segmented>
 <size/>
 <source>
  <database>
   GRAZPEDWRI-DX
  </database>
 </source>
 <object>
  <bndbox>
   <xmax>
    593
   </xmax>
   <xmin>
    560
   </xmin>
   <ymax>
    340
   </ymax>
   <ymin>
    265
   </ymin>
  </bndbox>
  <difficult>
   0
  </difficult>
  <name>
   text
  </name>
  <pose>
   Unspecified
  </pose>
  <truncated>
   0
  </truncated>
 </object>
</annotation>