<?xml version="1.0" encoding="utf-8"?>
<annotation>
 <filename>
  1393_0564640356_03_WRI-R1_F006.png
 </filename>
 <folder/>
 <path>
  1393_0564640356_03_WRI-R1_F006.png
 </path>
 <segmented>
  0
 </segmented>
 <size/>
 <source>
  <database>
   GRAZPEDWRI-DX
  </database>
 </source>
 <object>
  <bndbox>
   <xmax>
    392
   </xmax>
   <xmin>
    328
   </xmin>
   <ymax>
    456
   </ymax>
   <ymin>
    407
   </ymin>
  </bndbox>
  <difficult>
   0
  </difficult>
  <name>
   fracture
  </name>
  <pose>
   Unspecified
  </pose>
  <truncated>
   0
  </truncated>
 </object>
 <object>
  <bndbox>
   <xmax>
    284
   </xmax>
   <xmin>
    199
   </xmin>
   <ymax>
    533
   </ymax>
   <ymin>
    439
   </ymin>
  </bndbox>
  <difficult>
   0
  </difficult>
  <name>
   fracture
  </name>
  <pose>
   Unspecified
  </pose>
  <truncated>
   0
  </truncated>
 </object>
 <object>
  <bndbox>
   <xmax>
    496
   </xmax>
   <xmin>
    432
   </xmin>
   <ymax>
    580
   </ymax>
   <ymin>
    508
   </ymin>
  </bndbox>
  <difficult>
   0
  </difficult>
  <name>
   text
  </name>
  <pose>
   Unspecified
  </pose>
  <truncated>
   0
  </truncated>
 </object>
</annotation>