<?xml version="1.0" encoding="utf-8"?>
<annotation>
 <filename>
  1413_0931733098_01_WRI-R1_M010.png
 </filename>
 <folder/>
 <path>
  1413_0931733098_01_WRI-R1_M010.png
 </path>
 <segmented>
  0
 </segmented>
 <size/>
 <source>
  <database>
   GRAZPEDWRI-DX
  </database>
 </source>
 <object>
  <bndbox>
   <xmax>
    548
   </xmax>
   <xmin>
    494
   </xmin>
   <ymax>
    787
   </ymax>
   <ymin>
    671
   </ymin>
  </bndbox>
  <difficult>
   0
  </difficult>
  <name>
   text
  </name>
  <pose>
   Unspecified
  </pose>
  <truncated>
   0
  </truncated>
 </object>
 <object>
  <bndbox>
   <xmax>
    514
   </xmax>
   <xmin>
    489
   </xmin>
   <ymax>
    112
   </ymax>
   <ymin>
    81
   </ymin>
  </bndbox>
  <difficult>
   0
  </difficult>
  <name>
   text
  </name>
  <pose>
   Unspecified
  </pose>
  <truncated>
   0
  </truncated>
 </object>
 <object>
  <bndbox>
   <xmax>
    314
   </xmax>
   <xmin>
    152
   </xmin>
   <ymax>
    548
   </ymax>
   <ymin>
    482
   </ymin>
  </bndbox>
  <difficult>
   0
  </difficult>
  <name>
   fracture
  </name>
  <pose>
   Unspecified
  </pose>
  <truncated>
   0
  </truncated>
 </object>
</annotation>