<?xml version="1.0" encoding="utf-8"?>
<annotation>
 <filename>
  1479_0373779334_02_WRI-R1_F006.png
 </filename>
 <folder/>
 <path>
  1479_0373779334_02_WRI-R1_F006.png
 </path>
 <segmented>
  0
 </segmented>
 <size/>
 <source>
  <database>
   GRAZPEDWRI-DX
  </database>
 </source>
 <object>
  <bndbox>
   <xmax>
    527
   </xmax>
   <xmin>
    500
   </xmin>
   <ymax>
    219
   </ymax>
   <ymin>
    183
   </ymin>
  </bndbox>
  <difficult>
   0
  </difficult>
  <name>
   text
  </name>
  <pose>
   Unspecified
  </pose>
  <truncated>
   0
  </truncated>
 </object>
 <object>
  <bndbox>
   <xmax>
    303
   </xmax>
   <xmin>
    195
   </xmin>
   <ymax>
    634
   </ymax>
   <ymin>
    566
   </ymin>
  </bndbox>
  <difficult>
   0
  </difficult>
  <name>
   fracture
  </name>
  <pose>
   Unspecified
  </pose>
  <truncated>
   0
  </truncated>
 </object>
 <object>
  <bndbox>
   <xmax>
    402
   </xmax>
   <xmin>
    340
   </xmin>
   <ymax>
    608
   </ymax>
   <ymin>
    565
   </ymin>
  </bndbox>
  <difficult>
   0
  </difficult>
  <name>
   fracture
  </name>
  <pose>
   Unspecified
  </pose>
  <truncated>
   0
  </truncated>
 </object>
</annotation>