<?xml version="1.0" encoding="utf-8"?>
<annotation>
 <filename>
  1513_1254753138_01_WRI-R2_F008.png
 </filename>
 <folder/>
 <path>
  1513_1254753138_01_WRI-R2_F008.png
 </path>
 <segmented>
  0
 </segmented>
 <size/>
 <source>
  <database>
   GRAZPEDWRI-DX
  </database>
 </source>
 <object>
  <bndbox>
   <xmax>
    434
   </xmax>
   <xmin>
    403
   </xmin>
   <ymax>
    109
   </ymax>
   <ymin>
    72
   </ymin>
  </bndbox>
  <difficult>
   0
  </difficult>
  <name>
   text
  </name>
  <pose>
   Unspecified
  </pose>
  <truncated>
   0
  </truncated>
 </object>
 <object>
  <bndbox>
   <xmax>
    325
   </xmax>
   <xmin>
    211
   </xmin>
   <ymax>
    590
   </ymax>
   <ymin>
    516
   </ymin>
  </bndbox>
  <difficult>
   0
  </difficult>
  <name>
   fracture
  </name>
  <pose>
   Unspecified
  </pose>
  <truncated>
   0
  </truncated>
 </object>
</annotation>