<?xml version="1.0" encoding="utf-8"?>
<annotation>
 <filename>
  1786_1051711157_01_WRI-R2_F004.png
 </filename>
 <folder/>
 <path>
  1786_1051711157_01_WRI-R2_F004.png
 </path>
 <segmented>
  0
 </segmented>
 <size/>
 <source>
  <database>
   GRAZPEDWRI-DX
  </database>
 </source>
 <object>
  <bndbox>
   <xmax>
    423
   </xmax>
   <xmin>
    406
   </xmin>
   <ymax>
    51
   </ymax>
   <ymin>
    31
   </ymin>
  </bndbox>
  <difficult>
   0
  </difficult>
  <name>
   text
  </name>
  <pose>
   Unspecified
  </pose>
  <truncated>
   0
  </truncated>
 </object>
 <object>
  <bndbox>
   <xmax>
    492
   </xmax>
   <xmin>
    466
   </xmin>
   <ymax>
    132
   </ymax>
   <ymin>
    59
   </ymin>
  </bndbox>
  <difficult>
   0
  </difficult>
  <name>
   text
  </name>
  <pose>
   Unspecified
  </pose>
  <truncated>
   0
  </truncated>
 </object>
 <object>
  <bndbox>
   <xmax>
    239
   </xmax>
   <xmin>
    176
   </xmin>
   <ymax>
    456
   </ymax>
   <ymin>
    389
   </ymin>
  </bndbox>
  <difficult>
   0
  </difficult>
  <name>
   fracture
  </name>
  <pose>
   Unspecified
  </pose>
  <truncated>
   0
  </truncated>
 </object>
</annotation>