<?xml version="1.0" encoding="utf-8"?>
<annotation>
 <filename>
  1929_0894800987_02_WRI-L1_M009.png
 </filename>
 <folder/>
 <path>
  1929_0894800987_02_WRI-L1_M009.png
 </path>
 <segmented>
  0
 </segmented>
 <size/>
 <source>
  <database>
   GRAZPEDWRI-DX
  </database>
 </source>
 <object>
  <bndbox>
   <xmax>
    352
   </xmax>
   <xmin>
    211
   </xmin>
   <ymax>
    496
   </ymax>
   <ymin>
    422
   </ymin>
  </bndbox>
  <difficult>
   0
  </difficult>
  <name>
   fracture
  </name>
  <pose>
   Unspecified
  </pose>
  <truncated>
   0
  </truncated>
 </object>
 <object>
  <bndbox>
   <xmax>
    13
   </xmax>
   <xmin>
    0
   </xmin>
   <ymax>
    183
   </ymax>
   <ymin>
    162
   </ymin>
  </bndbox>
  <difficult>
   0
  </difficult>
  <name>
   text
  </name>
  <pose>
   Unspecified
  </pose>
  <truncated>
   0
  </truncated>
 </object>
 <object>
  <bndbox>
   <xmax>
    509
   </xmax>
   <xmin>
    505
   </xmin>
   <ymax>
    179
   </ymax>
   <ymin>
    161
   </ymin>
  </bndbox>
  <difficult>
   0
  </difficult>
  <name>
   text
  </name>
  <pose>
   Unspecified
  </pose>
  <truncated>
   0
  </truncated>
 </object>
 <object>
  <bndbox>
   <xmax>
    24
   </xmax>
   <xmin>
    0
   </xmin>
   <ymax>
    202
   </ymax>
   <ymin>
    185
   </ymin>
  </bndbox>
  <difficult>
   0
  </difficult>
  <name>
   text
  </name>
  <pose>
   Unspecified
  </pose>
  <truncated>
   0
  </truncated>
 </object>
</annotation>