<?xml version="1.0" encoding="utf-8"?>
<annotation>
 <filename>
  2023_0273259287_03_WRI-L1_M009.png
 </filename>
 <folder/>
 <path>
  2023_0273259287_03_WRI-L1_M009.png
 </path>
 <segmented>
  0
 </segmented>
 <size/>
 <source>
  <database>
   GRAZPEDWRI-DX
  </database>
 </source>
 <object>
  <bndbox>
   <xmax>
    205
   </xmax>
   <xmin>
    126
   </xmin>
   <ymax>
    479
   </ymax>
   <ymin>
    410
   </ymin>
  </bndbox>
  <difficult>
   0
  </difficult>
  <name>
   fracture
  </name>
  <pose>
   Unspecified
  </pose>
  <truncated>
   0
  </truncated>
 </object>
 <object>
  <bndbox>
   <xmax>
    365
   </xmax>
   <xmin>
    248
   </xmin>
   <ymax>
    512
   </ymax>
   <ymin>
    409
   </ymin>
  </bndbox>
  <difficult>
   0
  </difficult>
  <name>
   fracture
  </name>
  <pose>
   Unspecified
  </pose>
  <truncated>
   0
  </truncated>
 </object>
 <object>
  <bndbox>
   <xmax>
    574
   </xmax>
   <xmin>
    527
   </xmin>
   <ymax>
    549
   </ymax>
   <ymin>
    475
   </ymin>
  </bndbox>
  <difficult>
   0
  </difficult>
  <name>
   text
  </name>
  <pose>
   Unspecified
  </pose>
  <truncated>
   0
  </truncated>
 </object>
 <object>
  <bndbox>
   <xmax>
    209
   </xmax>
   <xmin>
    171
   </xmin>
   <ymax>
    619
   </ymax>
   <ymin>
    406
   </ymin>
  </bndbox>
  <difficult>
   0
  </difficult>
  <name>
   periostealreaction
  </name>
  <pose>
   Unspecified
  </pose>
  <truncated>
   0
  </truncated>
 </object>
 <object>
  <bndbox>
   <xmax>
    385
   </xmax>
   <xmin>
    317
   </xmin>
   <ymax>
    618
   </ymax>
   <ymin>
    395
   </ymin>
  </bndbox>
  <difficult>
   0
  </difficult>
  <name>
   periostealreaction
  </name>
  <pose>
   Unspecified
  </pose>
  <truncated>
   0
  </truncated>
 </object>
 <object>
  <bndbox>
   <xmax>
    260
   </xmax>
   <xmin>
    247
   </xmin>
   <ymax>
    461
   </ymax>
   <ymin>
    398
   </ymin>
  </bndbox>
  <difficult>
   0
  </difficult>
  <name>
   periostealreaction
  </name>
  <pose>
   Unspecified
  </pose>
  <truncated>
   0
  </truncated>
 </object>
</annotation>