<?xml version="1.0" encoding="utf-8"?>
<annotation>
 <filename>
  2155_1058508863_02_WRI-L2_F008.png
 </filename>
 <folder/>
 <path>
  2155_1058508863_02_WRI-L2_F008.png
 </path>
 <segmented>
  0
 </segmented>
 <size/>
 <source>
  <database>
   GRAZPEDWRI-DX
  </database>
 </source>
 <object>
  <bndbox>
   <xmax>
    277
   </xmax>
   <xmin>
    161
   </xmin>
   <ymax>
    561
   </ymax>
   <ymin>
    495
   </ymin>
  </bndbox>
  <difficult>
   0
  </difficult>
  <name>
   fracture
  </name>
  <pose>
   Unspecified
  </pose>
  <truncated>
   0
  </truncated>
 </object>
 <object>
  <bndbox>
   <xmax>
    36
   </xmax>
   <xmin>
    17
   </xmin>
   <ymax>
    150
   </ymax>
   <ymin>
    119
   </ymin>
  </bndbox>
  <difficult>
   0
  </difficult>
  <name>
   text
  </name>
  <pose>
   Unspecified
  </pose>
  <truncated>
   0
  </truncated>
 </object>
 <object>
  <bndbox>
   <xmax>
    18
   </xmax>
   <xmin>
    0
   </xmin>
   <ymax>
    77
   </ymax>
   <ymin>
    57
   </ymin>
  </bndbox>
  <difficult>
   0
  </difficult>
  <name>
   text
  </name>
  <pose>
   Unspecified
  </pose>
  <truncated>
   0
  </truncated>
 </object>
</annotation>