<?xml version="1.0" encoding="utf-8"?>
<annotation>
 <filename>
  2258_0345857595_01_WRI-R2_M011.png
 </filename>
 <folder/>
 <path>
  2258_0345857595_01_WRI-R2_M011.png
 </path>
 <segmented>
  0
 </segmented>
 <size/>
 <source>
  <database>
   GRAZPEDWRI-DX
  </database>
 </source>
 <object>
  <bndbox>
   <xmax>
    472
   </xmax>
   <xmin>
    418
   </xmin>
   <ymax>
    337
   </ymax>
   <ymin>
    259
   </ymin>
  </bndbox>
  <difficult>
   0
  </difficult>
  <name>
   text
  </name>
  <pose>
   Unspecified
  </pose>
  <truncated>
   0
  </truncated>
 </object>
 <object>
  <bndbox>
   <xmax>
    346
   </xmax>
   <xmin>
    236
   </xmin>
   <ymax>
    606
   </ymax>
   <ymin>
    547
   </ymin>
  </bndbox>
  <difficult>
   0
  </difficult>
  <name>
   fracture
  </name>
  <pose>
   Unspecified
  </pose>
  <truncated>
   0
  </truncated>
 </object>
</annotation>