<?xml version="1.0" encoding="utf-8"?>
<annotation>
 <filename>
  2319_0212855132_01_WRI-R1_M012.png
 </filename>
 <folder/>
 <path>
  2319_0212855132_01_WRI-R1_M012.png
 </path>
 <segmented>
  0
 </segmented>
 <size/>
 <source>
  <database>
   GRAZPEDWRI-DX
  </database>
 </source>
 <object>
  <bndbox>
   <xmax>
    648
   </xmax>
   <xmin>
    576
   </xmin>
   <ymax>
    487
   </ymax>
   <ymin>
    369
   </ymin>
  </bndbox>
  <difficult>
   0
  </difficult>
  <name>
   text
  </name>
  <pose>
   Unspecified
  </pose>
  <truncated>
   0
  </truncated>
 </object>
 <object>
  <bndbox>
   <xmax>
    415
   </xmax>
   <xmin>
    198
   </xmin>
   <ymax>
    562
   </ymax>
   <ymin>
    488
   </ymin>
  </bndbox>
  <difficult>
   0
  </difficult>
  <name>
   fracture
  </name>
  <pose>
   Unspecified
  </pose>
  <truncated>
   0
  </truncated>
 </object>
</annotation>