<?xml version="1.0" encoding="utf-8"?>
<annotation>
 <filename>
  2413_1086488934_02_WRI-L2_M013.png
 </filename>
 <folder/>
 <path>
  2413_1086488934_02_WRI-L2_M013.png
 </path>
 <segmented>
  0
 </segmented>
 <size/>
 <source>
  <database>
   GRAZPEDWRI-DX
  </database>
 </source>
 <object>
  <bndbox>
   <xmax>
    85
   </xmax>
   <xmin>
    58
   </xmin>
   <ymax>
    182
   </ymax>
   <ymin>
    146
   </ymin>
  </bndbox>
  <difficult>
   0
  </difficult>
  <name>
   text
  </name>
  <pose>
   Unspecified
  </pose>
  <truncated>
   0
  </truncated>
 </object>
 <object>
  <bndbox>
   <xmax>
    59
   </xmax>
   <xmin>
    51
   </xmin>
   <ymax>
    107
   </ymax>
   <ymin>
    92
   </ymin>
  </bndbox>
  <difficult>
   0
  </difficult>
  <name>
   text
  </name>
  <pose>
   Unspecified
  </pose>
  <truncated>
   0
  </truncated>
 </object>
 <object>
  <bndbox>
   <xmax>
    293
   </xmax>
   <xmin>
    153
   </xmin>
   <ymax>
    540
   </ymax>
   <ymin>
    457
   </ymin>
  </bndbox>
  <difficult>
   0
  </difficult>
  <name>
   fracture
  </name>
  <pose>
   Unspecified
  </pose>
  <truncated>
   0
  </truncated>
 </object>
</annotation>