<?xml version="1.0" encoding="utf-8"?>
<annotation>
 <filename>
  2443_0965289731_05_WRI-R2_M014.png
 </filename>
 <folder/>
 <path>
  2443_0965289731_05_WRI-R2_M014.png
 </path>
 <segmented>
  0
 </segmented>
 <size/>
 <source>
  <database>
   GRAZPEDWRI-DX
  </database>
 </source>
 <object>
  <bndbox>
   <xmax>
    584
   </xmax>
   <xmin>
    549
   </xmin>
   <ymax>
    417
   </ymax>
   <ymin>
    367
   </ymin>
  </bndbox>
  <difficult>
   0
  </difficult>
  <name>
   text
  </name>
  <pose>
   Unspecified
  </pose>
  <truncated>
   0
  </truncated>
 </object>
 <object>
  <bndbox>
   <xmax>
    653
   </xmax>
   <xmin>
    617
   </xmin>
   <ymax>
    630
   </ymax>
   <ymin>
    524
   </ymin>
  </bndbox>
  <difficult>
   0
  </difficult>
  <name>
   text
  </name>
  <pose>
   Unspecified
  </pose>
  <truncated>
   0
  </truncated>
 </object>
 <object>
  <bndbox>
   <xmax>
    485
   </xmax>
   <xmin>
    300
   </xmin>
   <ymax>
    1105
   </ymax>
   <ymin>
    979
   </ymin>
  </bndbox>
  <difficult>
   0
  </difficult>
  <name>
   fracture
  </name>
  <pose>
   Unspecified
  </pose>
  <truncated>
   0
  </truncated>
 </object>
</annotation>