<?xml version="1.0" encoding="utf-8"?>
<annotation>
 <filename>
  2580_0639597150_01_WRI-R2_M005.png
 </filename>
 <folder/>
 <path>
  2580_0639597150_01_WRI-R2_M005.png
 </path>
 <segmented>
  0
 </segmented>
 <size/>
 <source>
  <database>
   GRAZPEDWRI-DX
  </database>
 </source>
 <object>
  <bndbox>
   <xmax>
    311
   </xmax>
   <xmin>
    294
   </xmin>
   <ymax>
    70
   </ymax>
   <ymin>
    46
   </ymin>
  </bndbox>
  <difficult>
   0
  </difficult>
  <name>
   text
  </name>
  <pose>
   Unspecified
  </pose>
  <truncated>
   0
  </truncated>
 </object>
 <object>
  <bndbox>
   <xmax>
    218
   </xmax>
   <xmin>
    142
   </xmin>
   <ymax>
    329
   </ymax>
   <ymin>
    293
   </ymin>
  </bndbox>
  <difficult>
   0
  </difficult>
  <name>
   fracture
  </name>
  <pose>
   Unspecified
  </pose>
  <truncated>
   0
  </truncated>
 </object>
</annotation>