<?xml version="1.0" encoding="utf-8"?>
<annotation>
 <filename>
  2821_0372850758_01_WRI-L1_M013.png
 </filename>
 <folder/>
 <path>
  2821_0372850758_01_WRI-L1_M013.png
 </path>
 <segmented>
  0
 </segmented>
 <size/>
 <source>
  <database>
   GRAZPEDWRI-DX
  </database>
 </source>
 <object>
  <bndbox>
   <xmax>
    99
   </xmax>
   <xmin>
    35
   </xmin>
   <ymax>
    533
   </ymax>
   <ymin>
    405
   </ymin>
  </bndbox>
  <difficult>
   0
  </difficult>
  <name>
   text
  </name>
  <pose>
   Unspecified
  </pose>
  <truncated>
   0
  </truncated>
 </object>
 <object>
  <bndbox>
   <xmax>
    557
   </xmax>
   <xmin>
    400
   </xmin>
   <ymax>
    623
   </ymax>
   <ymin>
    530
   </ymin>
  </bndbox>
  <difficult>
   0
  </difficult>
  <name>
   fracture
  </name>
  <pose>
   Unspecified
  </pose>
  <truncated>
   0
  </truncated>
 </object>
 <object>
  <bndbox>
   <xmax>
    320
   </xmax>
   <xmin>
    253
   </xmin>
   <ymax>
    427
   </ymax>
   <ymin>
    361
   </ymin>
  </bndbox>
  <difficult>
   0
  </difficult>
  <name>
   fracture
  </name>
  <pose>
   Unspecified
  </pose>
  <truncated>
   0
  </truncated>
 </object>
</annotation>