<?xml version="1.0" encoding="utf-8"?>
<annotation>
 <filename>
  3147_0901636425_02_WRI-L1_M014.png
 </filename>
 <folder/>
 <path>
  3147_0901636425_02_WRI-L1_M014.png
 </path>
 <segmented>
  0
 </segmented>
 <size/>
 <source>
  <database>
   GRAZPEDWRI-DX
  </database>
 </source>
 <object>
  <bndbox>
   <xmax>
    21
   </xmax>
   <xmin>
    4
   </xmin>
   <ymax>
    776
   </ymax>
   <ymin>
    744
   </ymin>
  </bndbox>
  <difficult>
   0
  </difficult>
  <name>
   text
  </name>
  <pose>
   Unspecified
  </pose>
  <truncated>
   0
  </truncated>
 </object>
 <object>
  <bndbox>
   <xmax>
    171
   </xmax>
   <xmin>
    14
   </xmin>
   <ymax>
    920
   </ymax>
   <ymin>
    882
   </ymin>
  </bndbox>
  <difficult>
   0
  </difficult>
  <name>
   text
  </name>
  <pose>
   Unspecified
  </pose>
  <truncated>
   0
  </truncated>
 </object>
 <object>
  <bndbox>
   <xmax>
    17
   </xmax>
   <xmin>
    0
   </xmin>
   <ymax>
    882
   </ymax>
   <ymin>
    812
   </ymin>
  </bndbox>
  <difficult>
   0
  </difficult>
  <name>
   text
  </name>
  <pose>
   Unspecified
  </pose>
  <truncated>
   0
  </truncated>
 </object>
</annotation>