<?xml version="1.0" encoding="utf-8"?>
<annotation>
 <filename>
  3594_0331667659_01_WRI-R1_M014.png
 </filename>
 <folder/>
 <path>
  3594_0331667659_01_WRI-R1_M014.png
 </path>
 <segmented>
  0
 </segmented>
 <size/>
 <source>
  <database>
   GRAZPEDWRI-DX
  </database>
 </source>
 <object>
  <bndbox>
   <xmax>
    425
   </xmax>
   <xmin>
    266
   </xmin>
   <ymax>
    655
   </ymax>
   <ymin>
    565
   </ymin>
  </bndbox>
  <difficult>
   0
  </difficult>
  <name>
   fracture
  </name>
  <pose>
   Unspecified
  </pose>
  <truncated>
   0
  </truncated>
 </object>
 <object>
  <bndbox>
   <xmax>
    747
   </xmax>
   <xmin>
    714
   </xmin>
   <ymax>
    692
   </ymax>
   <ymin>
    572
   </ymin>
  </bndbox>
  <difficult>
   0
  </difficult>
  <name>
   text
  </name>
  <pose>
   Unspecified
  </pose>
  <truncated>
   0
  </truncated>
 </object>
 <object>
  <bndbox>
   <xmax>
    567
   </xmax>
   <xmin>
    496
   </xmin>
   <ymax>
    497
   </ymax>
   <ymin>
    425
   </ymin>
  </bndbox>
  <difficult>
   0
  </difficult>
  <name>
   fracture
  </name>
  <pose>
   Unspecified
  </pose>
  <truncated>
   0
  </truncated>
 </object>
</annotation>