<?xml version="1.0" encoding="utf-8"?>
<annotation>
 <filename>
  3679_0240154601_03_WRI-R1_F013.png
 </filename>
 <folder/>
 <path>
  3679_0240154601_03_WRI-R1_F013.png
 </path>
 <segmented>
  0
 </segmented>
 <size/>
 <source>
  <database>
   GRAZPEDWRI-DX
  </database>
 </source>
 <object>
  <bndbox>
   <xmax>
    705
   </xmax>
   <xmin>
    651
   </xmin>
   <ymax>
    812
   </ymax>
   <ymin>
    745
   </ymin>
  </bndbox>
  <difficult>
   0
  </difficult>
  <name>
   text
  </name>
  <pose>
   Unspecified
  </pose>
  <truncated>
   0
  </truncated>
 </object>
 <object>
  <bndbox>
   <xmax>
    403
   </xmax>
   <xmin>
    242
   </xmin>
   <ymax>
    682
   </ymax>
   <ymin>
    565
   </ymin>
  </bndbox>
  <difficult>
   0
  </difficult>
  <name>
   fracture
  </name>
  <pose>
   Unspecified
  </pose>
  <truncated>
   0
  </truncated>
 </object>
 <object>
  <bndbox>
   <xmax>
    507
   </xmax>
   <xmin>
    454
   </xmin>
   <ymax>
    521
   </ymax>
   <ymin>
    469
   </ymin>
  </bndbox>
  <difficult>
   0
  </difficult>
  <name>
   fracture
  </name>
  <pose>
   Unspecified
  </pose>
  <truncated>
   0
  </truncated>
 </object>
 <object>
  <bndbox>
   <xmax>
    512
   </xmax>
   <xmin>
    420
   </xmin>
   <ymax>
    630
   </ymax>
   <ymin>
    542
   </ymin>
  </bndbox>
  <difficult>
   0
  </difficult>
  <name>
   fracture
  </name>
  <pose>
   Unspecified
  </pose>
  <truncated>
   0
  </truncated>
 </object>
 <object>
  <bndbox>
   <xmax>
    415
   </xmax>
   <xmin>
    384
   </xmin>
   <ymax>
    888
   </ymax>
   <ymin>
    574
   </ymin>
  </bndbox>
  <difficult>
   0
  </difficult>
  <name>
   periostealreaction
  </name>
  <pose>
   Unspecified
  </pose>
  <truncated>
   0
  </truncated>
 </object>
 <object>
  <bndbox>
   <xmax>
    283
   </xmax>
   <xmin>
    252
   </xmin>
   <ymax>
    748
   </ymax>
   <ymin>
    634
   </ymin>
  </bndbox>
  <difficult>
   0
  </difficult>
  <name>
   periostealreaction
  </name>
  <pose>
   Unspecified
  </pose>
  <truncated>
   0
  </truncated>
 </object>
</annotation>