<?xml version="1.0" encoding="utf-8"?>
<annotation>
 <filename>
  3724_0481218066_01_WRI-R1_F010.png
 </filename>
 <folder/>
 <path>
  3724_0481218066_01_WRI-R1_F010.png
 </path>
 <segmented>
  0
 </segmented>
 <size/>
 <source>
  <database>
   GRAZPEDWRI-DX
  </database>
 </source>
 <object>
  <bndbox>
   <xmax>
    504
   </xmax>
   <xmin>
    470
   </xmin>
   <ymax>
    164
   </ymax>
   <ymin>
    126
   </ymin>
  </bndbox>
  <difficult>
   0
  </difficult>
  <name>
   text
  </name>
  <pose>
   Unspecified
  </pose>
  <truncated>
   0
  </truncated>
 </object>
 <object>
  <bndbox>
   <xmax>
    561
   </xmax>
   <xmin>
    505
   </xmin>
   <ymax>
    734
   </ymax>
   <ymin>
    615
   </ymin>
  </bndbox>
  <difficult>
   0
  </difficult>
  <name>
   text
  </name>
  <pose>
   Unspecified
  </pose>
  <truncated>
   0
  </truncated>
 </object>
 <object>
  <bndbox>
   <xmax>
    299
   </xmax>
   <xmin>
    172
   </xmin>
   <ymax>
    650
   </ymax>
   <ymin>
    575
   </ymin>
  </bndbox>
  <difficult>
   0
  </difficult>
  <name>
   fracture
  </name>
  <pose>
   Unspecified
  </pose>
  <truncated>
   0
  </truncated>
 </object>
</annotation>