<?xml version="1.0" encoding="utf-8"?>
<annotation>
 <filename>
  3833_0227901695_04_WRI-L1_F006.png
 </filename>
 <folder/>
 <path>
  3833_0227901695_04_WRI-L1_F006.png
 </path>
 <segmented>
  0
 </segmented>
 <size/>
 <source>
  <database>
   GRAZPEDWRI-DX
  </database>
 </source>
 <object>
  <bndbox>
   <xmax>
    79
   </xmax>
   <xmin>
    60
   </xmin>
   <ymax>
    77
   </ymax>
   <ymin>
    45
   </ymin>
  </bndbox>
  <difficult>
   0
  </difficult>
  <name>
   text
  </name>
  <pose>
   Unspecified
  </pose>
  <truncated>
   0
  </truncated>
 </object>
 <object>
  <bndbox>
   <xmax>
    359
   </xmax>
   <xmin>
    269
   </xmin>
   <ymax>
    531
   </ymax>
   <ymin>
    477
   </ymin>
  </bndbox>
  <difficult>
   0
  </difficult>
  <name>
   fracture
  </name>
  <pose>
   Unspecified
  </pose>
  <truncated>
   0
  </truncated>
 </object>
 <object>
  <bndbox>
   <xmax>
    210
   </xmax>
   <xmin>
    127
   </xmin>
   <ymax>
    475
   </ymax>
   <ymin>
    410
   </ymin>
  </bndbox>
  <difficult>
   0
  </difficult>
  <name>
   fracture
  </name>
  <pose>
   Unspecified
  </pose>
  <truncated>
   0
  </truncated>
 </object>
</annotation>