<?xml version="1.0" encoding="utf-8"?>
<annotation>
 <filename>
  3956_0792133904_02_WRI-L2_M015.png
 </filename>
 <folder/>
 <path>
  3956_0792133904_02_WRI-L2_M015.png
 </path>
 <segmented>
  0
 </segmented>
 <size/>
 <source>
  <database>
   GRAZPEDWRI-DX
  </database>
 </source>
 <object>
  <bndbox>
   <xmax>
    294
   </xmax>
   <xmin>
    167
   </xmin>
   <ymax>
    855
   </ymax>
   <ymin>
    725
   </ymin>
  </bndbox>
  <difficult>
   0
  </difficult>
  <name>
   fracture
  </name>
  <pose>
   Unspecified
  </pose>
  <truncated>
   0
  </truncated>
 </object>
 <object>
  <bndbox>
   <xmax>
    87
   </xmax>
   <xmin>
    63
   </xmin>
   <ymax>
    392
   </ymax>
   <ymin>
    350
   </ymin>
  </bndbox>
  <difficult>
   0
  </difficult>
  <name>
   text
  </name>
  <pose>
   Unspecified
  </pose>
  <truncated>
   0
  </truncated>
 </object>
 <object>
  <bndbox>
   <xmax>
    59
   </xmax>
   <xmin>
    31
   </xmin>
   <ymax>
    149
   </ymax>
   <ymin>
    126
   </ymin>
  </bndbox>
  <difficult>
   0
  </difficult>
  <name>
   text
  </name>
  <pose>
   Unspecified
  </pose>
  <truncated>
   0
  </truncated>
 </object>
</annotation>