<?xml version="1.0" encoding="utf-8"?>
<annotation>
 <filename>
  4031_0256602179_01_WRI-R2_M016.png
 </filename>
 <folder/>
 <path>
  4031_0256602179_01_WRI-R2_M016.png
 </path>
 <segmented>
  0
 </segmented>
 <size/>
 <source>
  <database>
   GRAZPEDWRI-DX
  </database>
 </source>
 <object>
  <bndbox>
   <xmax>
    435
   </xmax>
   <xmin>
    391
   </xmin>
   <ymax>
    116
   </ymax>
   <ymin>
    40
   </ymin>
  </bndbox>
  <difficult>
   0
  </difficult>
  <name>
   text
  </name>
  <pose>
   Unspecified
  </pose>
  <truncated>
   0
  </truncated>
 </object>
 <object>
  <bndbox>
   <xmax>
    392
   </xmax>
   <xmin>
    246
   </xmin>
   <ymax>
    564
   </ymax>
   <ymin>
    472
   </ymin>
  </bndbox>
  <difficult>
   0
  </difficult>
  <name>
   fracture
  </name>
  <pose>
   Unspecified
  </pose>
  <truncated>
   0
  </truncated>
 </object>
 <object>
  <bndbox>
   <xmax>
    278
   </xmax>
   <xmin>
    161
   </xmin>
   <ymax>
    839
   </ymax>
   <ymin>
    411
   </ymin>
  </bndbox>
  <difficult>
   0
  </difficult>
  <name>
   pronatorsign
  </name>
  <pose>
   Unspecified
  </pose>
  <truncated>
   0
  </truncated>
 </object>
</annotation>