<?xml version="1.0" encoding="utf-8"?>
<annotation>
 <filename>
  4186_0288020189_02_WRI-L1_M013.png
 </filename>
 <folder/>
 <path>
  4186_0288020189_02_WRI-L1_M013.png
 </path>
 <segmented>
  0
 </segmented>
 <size/>
 <source>
  <database>
   GRAZPEDWRI-DX
  </database>
 </source>
 <object>
  <bndbox>
   <xmax>
    63
   </xmax>
   <xmin>
    21
   </xmin>
   <ymax>
    519
   </ymax>
   <ymin>
    448
   </ymin>
  </bndbox>
  <difficult>
   0
  </difficult>
  <name>
   text
  </name>
  <pose>
   Unspecified
  </pose>
  <truncated>
   0
  </truncated>
 </object>
</annotation>