<?xml version="1.0" encoding="utf-8"?>
<annotation>
 <filename>
  4240_0328086664_01_WRI-L2_M004.png
 </filename>
 <folder/>
 <path>
  4240_0328086664_01_WRI-L2_M004.png
 </path>
 <segmented>
  0
 </segmented>
 <size/>
 <source>
  <database>
   GRAZPEDWRI-DX
  </database>
 </source>
 <object>
  <bndbox>
   <xmax>
    242
   </xmax>
   <xmin>
    148
   </xmin>
   <ymax>
    504
   </ymax>
   <ymin>
    437
   </ymin>
  </bndbox>
  <difficult>
   0
  </difficult>
  <name>
   fracture
  </name>
  <pose>
   Unspecified
  </pose>
  <truncated>
   0
  </truncated>
 </object>
 <object>
  <bndbox>
   <xmax>
    135
   </xmax>
   <xmin>
    82
   </xmin>
   <ymax>
    550
   </ymax>
   <ymin>
    500
   </ymin>
  </bndbox>
  <difficult>
   0
  </difficult>
  <name>
   fracture
  </name>
  <pose>
   Unspecified
  </pose>
  <truncated>
   0
  </truncated>
 </object>
 <object>
  <bndbox>
   <xmax>
    185
   </xmax>
   <xmin>
    114
   </xmin>
   <ymax>
    724
   </ymax>
   <ymin>
    414
   </ymin>
  </bndbox>
  <difficult>
   0
  </difficult>
  <name>
   periostealreaction
  </name>
  <pose>
   Unspecified
  </pose>
  <truncated>
   0
  </truncated>
 </object>
 <object>
  <bndbox>
   <xmax>
    90
   </xmax>
   <xmin>
    79
   </xmin>
   <ymax>
    745
   </ymax>
   <ymin>
    544
   </ymin>
  </bndbox>
  <difficult>
   0
  </difficult>
  <name>
   periostealreaction
  </name>
  <pose>
   Unspecified
  </pose>
  <truncated>
   0
  </truncated>
 </object>
 <object>
  <bndbox>
   <xmax>
    87
   </xmax>
   <xmin>
    77
   </xmin>
   <ymax>
    517
   </ymax>
   <ymin>
    432
   </ymin>
  </bndbox>
  <difficult>
   0
  </difficult>
  <name>
   periostealreaction
  </name>
  <pose>
   Unspecified
  </pose>
  <truncated>
   0
  </truncated>
 </object>
 <object>
  <bndbox>
   <xmax>
    45
   </xmax>
   <xmin>
    10
   </xmin>
   <ymax>
    106
   </ymax>
   <ymin>
    33
   </ymin>
  </bndbox>
  <difficult>
   0
  </difficult>
  <name>
   text
  </name>
  <pose>
   Unspecified
  </pose>
  <truncated>
   0
  </truncated>
 </object>
</annotation>