<?xml version="1.0" encoding="utf-8"?>
<annotation>
 <filename>
  4387_0742809294_04_WRI-R2_M015.png
 </filename>
 <folder/>
 <path>
  4387_0742809294_04_WRI-R2_M015.png
 </path>
 <segmented>
  0
 </segmented>
 <size/>
 <source>
  <database>
   GRAZPEDWRI-DX
  </database>
 </source>
 <object>
  <bndbox>
   <xmax>
    501
   </xmax>
   <xmin>
    413
   </xmin>
   <ymax>
    413
   </ymax>
   <ymin>
    289
   </ymin>
  </bndbox>
  <difficult>
   0
  </difficult>
  <name>
   text
  </name>
  <pose>
   Unspecified
  </pose>
  <truncated>
   0
  </truncated>
 </object>
</annotation>