<?xml version="1.0" encoding="utf-8"?>
<annotation>
 <filename>
  4429_1017177708_06_WRI-L2_M006.png
 </filename>
 <folder/>
 <path>
  4429_1017177708_06_WRI-L2_M006.png
 </path>
 <segmented>
  0
 </segmented>
 <size/>
 <source>
  <database>
   GRAZPEDWRI-DX
  </database>
 </source>
 <object>
  <bndbox>
   <xmax>
    249
   </xmax>
   <xmin>
    201
   </xmin>
   <ymax>
    547
   </ymax>
   <ymin>
    427
   </ymin>
  </bndbox>
  <difficult>
   0
  </difficult>
  <name>
   periostealreaction
  </name>
  <pose>
   Unspecified
  </pose>
  <truncated>
   0
  </truncated>
 </object>
 <object>
  <bndbox>
   <xmax>
    242
   </xmax>
   <xmin>
    141
   </xmin>
   <ymax>
    475
   </ymax>
   <ymin>
    400
   </ymin>
  </bndbox>
  <difficult>
   0
  </difficult>
  <name>
   fracture
  </name>
  <pose>
   Unspecified
  </pose>
  <truncated>
   0
  </truncated>
 </object>
 <object>
  <bndbox>
   <xmax>
    15
   </xmax>
   <xmin>
    2
   </xmin>
   <ymax>
    60
   </ymax>
   <ymin>
    40
   </ymin>
  </bndbox>
  <difficult>
   0
  </difficult>
  <name>
   text
  </name>
  <pose>
   Unspecified
  </pose>
  <truncated>
   0
  </truncated>
 </object>
</annotation>