<?xml version="1.0" encoding="utf-8"?>
<annotation>
 <filename>
  4672_1041753147_07_WRI-R1_F010.png
 </filename>
 <folder/>
 <path>
  4672_1041753147_07_WRI-R1_F010.png
 </path>
 <segmented>
  0
 </segmented>
 <size/>
 <source>
  <database>
   GRAZPEDWRI-DX
  </database>
 </source>
 <object>
  <bndbox>
   <xmax>
    496
   </xmax>
   <xmin>
    397
   </xmin>
   <ymax>
    619
   </ymax>
   <ymin>
    551
   </ymin>
  </bndbox>
  <difficult>
   0
  </difficult>
  <name>
   fracture
  </name>
  <pose>
   Unspecified
  </pose>
  <truncated>
   0
  </truncated>
 </object>
 <object>
  <bndbox>
   <xmax>
    371
   </xmax>
   <xmin>
    198
   </xmin>
   <ymax>
    610
   </ymax>
   <ymin>
    532
   </ymin>
  </bndbox>
  <difficult>
   0
  </difficult>
  <name>
   fracture
  </name>
  <pose>
   Unspecified
  </pose>
  <truncated>
   0
  </truncated>
 </object>
 <object>
  <bndbox>
   <xmax>
    660
   </xmax>
   <xmin>
    607
   </xmin>
   <ymax>
    417
   </ymax>
   <ymin>
    336
   </ymin>
  </bndbox>
  <difficult>
   0
  </difficult>
  <name>
   text
  </name>
  <pose>
   Unspecified
  </pose>
  <truncated>
   0
  </truncated>
 </object>
 <object>
  <bndbox>
   <xmax>
    375
   </xmax>
   <xmin>
    92
   </xmin>
   <ymax>
    643
   </ymax>
   <ymin>
    350
   </ymin>
  </bndbox>
  <difficult>
   0
  </difficult>
  <name>
   metal
  </name>
  <pose>
   Unspecified
  </pose>
  <truncated>
   0
  </truncated>
 </object>
 <object>
  <bndbox>
   <xmax>
    488
   </xmax>
   <xmin>
    407
   </xmin>
   <ymax>
    1001
   </ymax>
   <ymin>
    594
   </ymin>
  </bndbox>
  <difficult>
   0
  </difficult>
  <name>
   periostealreaction
  </name>
  <pose>
   Unspecified
  </pose>
  <truncated>
   0
  </truncated>
 </object>
 <object>
  <bndbox>
   <xmax>
    348
   </xmax>
   <xmin>
    327
   </xmin>
   <ymax>
    772
   </ymax>
   <ymin>
    617
   </ymin>
  </bndbox>
  <difficult>
   0
  </difficult>
  <name>
   periostealreaction
  </name>
  <pose>
   Unspecified
  </pose>
  <truncated>
   0
  </truncated>
 </object>
</annotation>