<?xml version="1.0" encoding="utf-8"?>
<annotation>
 <filename>
  4682_1113809228_01_WRI-L2_M006.png
 </filename>
 <folder/>
 <path>
  4682_1113809228_01_WRI-L2_M006.png
 </path>
 <segmented>
  0
 </segmented>
 <size/>
 <source>
  <database>
   GRAZPEDWRI-DX
  </database>
 </source>
 <object>
  <bndbox>
   <xmax>
    236
   </xmax>
   <xmin>
    151
   </xmin>
   <ymax>
    516
   </ymax>
   <ymin>
    462
   </ymin>
  </bndbox>
  <difficult>
   0
  </difficult>
  <name>
   fracture
  </name>
  <pose>
   Unspecified
  </pose>
  <truncated>
   0
  </truncated>
 </object>
 <object>
  <bndbox>
   <xmax>
    53
   </xmax>
   <xmin>
    9
   </xmin>
   <ymax>
    346
   </ymax>
   <ymin>
    272
   </ymin>
  </bndbox>
  <difficult>
   0
  </difficult>
  <name>
   text
  </name>
  <pose>
   Unspecified
  </pose>
  <truncated>
   0
  </truncated>
 </object>
</annotation>