<?xml version="1.0" encoding="utf-8"?>
<annotation>
 <filename>
  4888_0953127229_01_WRI-R2_F014.png
 </filename>
 <folder/>
 <path>
  4888_0953127229_01_WRI-R2_F014.png
 </path>
 <segmented>
  0
 </segmented>
 <size/>
 <source>
  <database>
   GRAZPEDWRI-DX
  </database>
 </source>
 <object>
  <bndbox>
   <xmax>
    424
   </xmax>
   <xmin>
    396
   </xmin>
   <ymax>
    406
   </ymax>
   <ymin>
    369
   </ymin>
  </bndbox>
  <difficult>
   0
  </difficult>
  <name>
   text
  </name>
  <pose>
   Unspecified
  </pose>
  <truncated>
   0
  </truncated>
 </object>
 <object>
  <bndbox>
   <xmax>
    466
   </xmax>
   <xmin>
    450
   </xmin>
   <ymax>
    973
   </ymax>
   <ymin>
    908
   </ymin>
  </bndbox>
  <difficult>
   0
  </difficult>
  <name>
   text
  </name>
  <pose>
   Unspecified
  </pose>
  <truncated>
   0
  </truncated>
 </object>
</annotation>