<?xml version="1.0" encoding="utf-8"?>
<annotation>
 <filename>
  5182_1193989187_02_WRI-R2_M013.png
 </filename>
 <folder/>
 <path>
  5182_1193989187_02_WRI-R2_M013.png
 </path>
 <segmented>
  0
 </segmented>
 <size/>
 <source>
  <database>
   GRAZPEDWRI-DX
  </database>
 </source>
 <object>
  <bndbox>
   <xmax>
    606
   </xmax>
   <xmin>
    572
   </xmin>
   <ymax>
    357
   </ymax>
   <ymin>
    320
   </ymin>
  </bndbox>
  <difficult>
   0
  </difficult>
  <name>
   text
  </name>
  <pose>
   Unspecified
  </pose>
  <truncated>
   0
  </truncated>
 </object>
 <object>
  <bndbox>
   <xmax>
    453
   </xmax>
   <xmin>
    261
   </xmin>
   <ymax>
    491
   </ymax>
   <ymin>
    385
   </ymin>
  </bndbox>
  <difficult>
   0
  </difficult>
  <name>
   fracture
  </name>
  <pose>
   Unspecified
  </pose>
  <truncated>
   0
  </truncated>
 </object>
 <object>
  <bndbox>
   <xmax>
    667
   </xmax>
   <xmin>
    640
   </xmin>
   <ymax>
    971
   </ymax>
   <ymin>
    902
   </ymin>
  </bndbox>
  <difficult>
   0
  </difficult>
  <name>
   text
  </name>
  <pose>
   Unspecified
  </pose>
  <truncated>
   0
  </truncated>
 </object>
</annotation>