<?xml version="1.0" encoding="utf-8"?>
<annotation>
 <filename>
  5409_0207338802_01_WRI-R1_F006.png
 </filename>
 <folder/>
 <path>
  5409_0207338802_01_WRI-R1_F006.png
 </path>
 <segmented>
  0
 </segmented>
 <size/>
 <source>
  <database>
   GRAZPEDWRI-DX
  </database>
 </source>
 <object>
  <bndbox>
   <xmax>
    530
   </xmax>
   <xmin>
    473
   </xmin>
   <ymax>
    383
   </ymax>
   <ymin>
    311
   </ymin>
  </bndbox>
  <difficult>
   0
  </difficult>
  <name>
   text
  </name>
  <pose>
   Unspecified
  </pose>
  <truncated>
   0
  </truncated>
 </object>
 <object>
  <bndbox>
   <xmax>
    297
   </xmax>
   <xmin>
    180
   </xmin>
   <ymax>
    591
   </ymax>
   <ymin>
    537
   </ymin>
  </bndbox>
  <difficult>
   0
  </difficult>
  <name>
   fracture
  </name>
  <pose>
   Unspecified
  </pose>
  <truncated>
   0
  </truncated>
 </object>
 <object>
  <bndbox>
   <xmax>
    410
   </xmax>
   <xmin>
    335
   </xmin>
   <ymax>
    549
   </ymax>
   <ymin>
    506
   </ymin>
  </bndbox>
  <difficult>
   0
  </difficult>
  <name>
   fracture
  </name>
  <pose>
   Unspecified
  </pose>
  <truncated>
   0
  </truncated>
 </object>
</annotation>