<?xml version="1.0" encoding="utf-8"?>
<annotation>
 <filename>
  5668_1219431475_01_WRI-R1_M013.png
 </filename>
 <folder/>
 <path>
  5668_1219431475_01_WRI-R1_M013.png
 </path>
 <segmented>
  0
 </segmented>
 <size/>
 <source>
  <database>
   GRAZPEDWRI-DX
  </database>
 </source>
 <object>
  <bndbox>
   <xmax>
    699
   </xmax>
   <xmin>
    667
   </xmin>
   <ymax>
    219
   </ymax>
   <ymin>
    181
   </ymin>
  </bndbox>
  <difficult>
   0
  </difficult>
  <name>
   text
  </name>
  <pose>
   Unspecified
  </pose>
  <truncated>
   0
  </truncated>
 </object>
 <object>
  <bndbox>
   <xmax>
    559
   </xmax>
   <xmin>
    445
   </xmin>
   <ymax>
    616
   </ymax>
   <ymin>
    536
   </ymin>
  </bndbox>
  <difficult>
   0
  </difficult>
  <name>
   fracture
  </name>
  <pose>
   Unspecified
  </pose>
  <truncated>
   0
  </truncated>
 </object>
 <object>
  <bndbox>
   <xmax>
    716
   </xmax>
   <xmin>
    687
   </xmin>
   <ymax>
    311
   </ymax>
   <ymin>
    245
   </ymin>
  </bndbox>
  <difficult>
   0
  </difficult>
  <name>
   text
  </name>
  <pose>
   Unspecified
  </pose>
  <truncated>
   0
  </truncated>
 </object>
 <object>
  <bndbox>
   <xmax>
    386
   </xmax>
   <xmin>
    241
   </xmin>
   <ymax>
    719
   </ymax>
   <ymin>
    631
   </ymin>
  </bndbox>
  <difficult>
   0
  </difficult>
  <name>
   fracture
  </name>
  <pose>
   Unspecified
  </pose>
  <truncated>
   0
  </truncated>
 </object>
</annotation>