<?xml version="1.0" encoding="utf-8"?>
<annotation>
 <filename>
  5727_0253381660_02_WRI-L2_M007.png
 </filename>
 <folder/>
 <path>
  5727_0253381660_02_WRI-L2_M007.png
 </path>
 <segmented>
  0
 </segmented>
 <size/>
 <source>
  <database>
   GRAZPEDWRI-DX
  </database>
 </source>
 <object>
  <bndbox>
   <xmax>
    560
   </xmax>
   <xmin>
    509
   </xmin>
   <ymax>
    173
   </ymax>
   <ymin>
    60
   </ymin>
  </bndbox>
  <difficult>
   0
  </difficult>
  <name>
   text
  </name>
  <pose>
   Unspecified
  </pose>
  <truncated>
   0
  </truncated>
 </object>
 <object>
  <bndbox>
   <xmax>
    337
   </xmax>
   <xmin>
    249
   </xmin>
   <ymax>
    673
   </ymax>
   <ymin>
    573
   </ymin>
  </bndbox>
  <difficult>
   0
  </difficult>
  <name>
   fracture
  </name>
  <pose>
   Unspecified
  </pose>
  <truncated>
   0
  </truncated>
 </object>
 <object>
  <bndbox>
   <xmax>
    320
   </xmax>
   <xmin>
    179
   </xmin>
   <ymax>
    761
   </ymax>
   <ymin>
    352
   </ymin>
  </bndbox>
  <difficult>
   0
  </difficult>
  <name>
   metal
  </name>
  <pose>
   Unspecified
  </pose>
  <truncated>
   0
  </truncated>
 </object>
</annotation>