<?xml version="1.0" encoding="utf-8"?>
<annotation>
 <filename>
  5912_0565607087_01_WRI-L1_F010.png
 </filename>
 <folder/>
 <path>
  5912_0565607087_01_WRI-L1_F010.png
 </path>
 <segmented>
  0
 </segmented>
 <size/>
 <source>
  <database>
   GRAZPEDWRI-DX
  </database>
 </source>
 <object>
  <bndbox>
   <xmax>
    68
   </xmax>
   <xmin>
    54
   </xmin>
   <ymax>
    599
   </ymax>
   <ymin>
    574
   </ymin>
  </bndbox>
  <difficult>
   0
  </difficult>
  <name>
   text
  </name>
  <pose>
   Unspecified
  </pose>
  <truncated>
   0
  </truncated>
 </object>
 <object>
  <bndbox>
   <xmax>
    43
   </xmax>
   <xmin>
    15
   </xmin>
   <ymax>
    704
   </ymax>
   <ymin>
    677
   </ymin>
  </bndbox>
  <difficult>
   0
  </difficult>
  <name>
   text
  </name>
  <pose>
   Unspecified
  </pose>
  <truncated>
   0
  </truncated>
 </object>
</annotation>